just_talk/__init__.py
just_talk/__main__.py
just_talk/comms.py
just_talk/messages.py
just_talk/model.py
just_talk/xml/Day.xml
just_talk/xml/GraphicTrack.xml
just_talk/xml/Node.xml
just_talk/xml/Play.xml
just_talk/xml/Playlist.xml
just_talk/xml/Track.xml
just_talk/xml/Trigger.xml
just_talk/xml/VideoTrack.xml
just_talk-0.1.3.dist-info/DESCRIPTION.rst
just_talk-0.1.3.dist-info/METADATA
just_talk-0.1.3.dist-info/RECORD
just_talk-0.1.3.dist-info/WHEEL
just_talk-0.1.3.dist-info/metadata.json
just_talk-0.1.3.dist-info/top_level.txt
