Metadata-Version: 2.0
Name: just-talk
Version: 0.1.3
Summary: Python package to use the TOA comms protocol
Home-page: https://github.com/magarnicle/just_talk
Author: Matthew Rademaker
Author-email: matthew@acctv.com.au
License: LICENSE
Download-URL: https://github.com/magarnicle/just_talk/archive/00.01.01.tar.gz
Keywords: tools on air toa just play video tv
Platform: UNKNOWN
Classifier: Development Status :: 4 - Beta
Classifier: Environment :: MacOS X
Classifier: Intended Audience :: Telecommunications Industry
Classifier: License :: Public Domain
Classifier: Natural Language :: English
Classifier: Programming Language :: Python :: 2.7
Classifier: Topic :: Multimedia :: Video
